pyrodantic/__init__.py
pyrodantic/document.py
pyrodantic-0.0.7.dist-info/LICENSE
pyrodantic-0.0.7.dist-info/METADATA
pyrodantic-0.0.7.dist-info/WHEEL
pyrodantic-0.0.7.dist-info/top_level.txt
pyrodantic-0.0.7.dist-info/RECORD
