Metadata-Version: 2.1
Name: pyrodantic
Version: 0.0.7
Summary: Pydantic models for Firestore
Home-page: https://github.com/mgwilliams/pyrodantic
Author: Matthew Williams
Author-email: mgwilliams@gmail.com
License: UNKNOWN
Platform: UNKNOWN
Classifier: Development Status :: 3 - Alpha
Classifier: Intended Audience :: Developers
Classifier: Programming Language :: Python :: 3
Classifier: License :: OSI Approved :: MIT License
Classifier: Operating System :: OS Independent
Requires-Python: >=3.6
Requires-Dist: pydantic
Requires-Dist: google-cloud-firestore
